filedate/__init__.py
filedate/__main__.py
filedate/Utils/Copy.py
filedate/Utils/Keep.py
filedate/Utils/Name.py
filedate/Utils/__init__.py
filedate-2.0.dist-info/METADATA
filedate-2.0.dist-info/WHEEL
filedate-2.0.dist-info/top_level.txt
filedate-2.0.dist-info/RECORD
